passivlingo_dictionary/Dictionary.py
passivlingo_dictionary/TextProcessor.py
passivlingo_dictionary/__init__.py
passivlingo_dictionary/encoders/WordEncoder.py
passivlingo_dictionary/extractors/AdjectiveExtractor.py
passivlingo_dictionary/extractors/AntonymExtractor.py
passivlingo_dictionary/extractors/CombinedExtractor.py
passivlingo_dictionary/extractors/EntailmentExtractor.py
passivlingo_dictionary/extractors/Extractor.py
passivlingo_dictionary/extractors/GenericExtractor.py
passivlingo_dictionary/extractors/HolonymExtractor.py
passivlingo_dictionary/extractors/HypernymExtractor.py
passivlingo_dictionary/extractors/HyponymExtractor.py
passivlingo_dictionary/extractors/MeronymExtractor.py
passivlingo_dictionary/extractors/PosExtractor.py
passivlingo_dictionary/helpers/CommonHelper.py
passivlingo_dictionary/helpers/Constants.py
passivlingo_dictionary/helpers/FactoryMethods.py
passivlingo_dictionary/helpers/SearchChainFactory.py
passivlingo_dictionary/lemmatizers/DefaultLemmatizer.py
passivlingo_dictionary/lemmatizers/Lemmatizer.py
passivlingo_dictionary/lemmatizers/SpacyLemmatizer.py
passivlingo_dictionary/models/BaseWord.py
passivlingo_dictionary/models/ContextWord.py
passivlingo_dictionary/models/GenericLanguageDescriptions.py
passivlingo_dictionary/models/LanguageDescriptions.py
passivlingo_dictionary/models/LinguisticCounter.py
passivlingo_dictionary/models/SearchParam.py
passivlingo_dictionary/models/Word.py
passivlingo_dictionary/posTaggers/NltkPosTagger.py
passivlingo_dictionary/posTaggers/PosTagger.py
passivlingo_dictionary/posTaggers/SpacyPosTagger.py
passivlingo_dictionary/searchChains/CategorySearchChain.py
passivlingo_dictionary/searchChains/ContainerSearchChain.py
passivlingo_dictionary/searchChains/DefaultSearchChain.py
passivlingo_dictionary/searchChains/IliSearchChain.py
passivlingo_dictionary/searchChains/LemmaSearchChain.py
passivlingo_dictionary/searchChains/MtSearchChain.py
passivlingo_dictionary/searchChains/PosSearchChain.py
passivlingo_dictionary-1.0.2.dist-info/LICENSE
passivlingo_dictionary-1.0.2.dist-info/METADATA
passivlingo_dictionary-1.0.2.dist-info/WHEEL
passivlingo_dictionary-1.0.2.dist-info/top_level.txt
passivlingo_dictionary-1.0.2.dist-info/RECORD
