Metadata-Version: 2.1
Name: passivlingo-dictionary
Version: 1.0.2
Summary: Python package for accessing OWN and NLTK wordnet ontologies
Home-page: https://github.com/pssvlng/passivlingo-dictionary
Author: passivlingo
Author-email: info@passivlingo.com
License: GPL 3
Platform: UNKNOWN
Classifier: Intended Audience :: Developers
Classifier: Topic :: Software Development :: Libraries :: Python Modules
Classifier: Programming Language :: Python :: 3
License-File: LICENSE
Requires-Dist: gtts
Requires-Dist: nltk
Requires-Dist: playsound
Requires-Dist: pyttsx3
Requires-Dist: spacy
Requires-Dist: textblob
Requires-Dist: wn
